ronbun/__init__.py
ronbun/readme.py
ronbun-0.9.1.dist-info/METADATA
ronbun-0.9.1.dist-info/WHEEL
ronbun-0.9.1.dist-info/entry_points.txt
ronbun-0.9.1.dist-info/licenses/LICENSE
ronbun-0.9.1.dist-info/RECORD
