Metadata-Version: 2.4
Name: ronbun
Version: 0.9.1
Summary: The Sample Programs README Automation Tool
License: MIT
License-File: LICENSE
Author: Jeremy Grifski
Author-email: jeremy.grifski@therenegadecoder.com
Requires-Python: >=3.9,<4.0
Classifier: Development Status :: 5 - Production/Stable
Classifier: License :: OSI Approved :: MIT License
Classifier: Operating System :: OS Independent
Classifier: Programming Language :: Python :: 3
Classifier: Programming Language :: Python :: 3.9
Classifier: Programming Language :: Python :: 3.10
Classifier: Programming Language :: Python :: 3.11
Classifier: Programming Language :: Python :: 3.12
Classifier: Programming Language :: Python :: 3.13
Classifier: Programming Language :: Python :: 3.14
Requires-Dist: snakemd (>=2.3.0,<3.0.0)
Requires-Dist: subete (>=0.21.0,<0.22.0)
Project-URL: Homepage, https://therenegadecoder.com
Project-URL: Repository, https://github.com/TheRenegadeCoder/sample-programs-readmes
